solop/__init__.py
solop/cli.py
solop/file_utils.py
solop/md_writer.py
solop/project_utils.py
solop/task_utils.py
solop-1.0.0.dist-info/METADATA
solop-1.0.0.dist-info/WHEEL
solop-1.0.0.dist-info/entry_points.txt
solop-1.0.0.dist-info/licenses/LICENSE
solop-1.0.0.dist-info/RECORD
