Metadata-Version: 2.3
Name: solop
Version: 1.0.0
Summary: A command line tool for generating and maintaining project development tasks
Project-URL: Homepage, https://github.com/niallantony/SoloP
Author-email: Niall Craven <craven.niall@gmail.com>
License: MIT License
Keywords: backlog,markdown,progress,project management,task,to do
Classifier: Development Status :: 4 - Beta
Classifier: Environment :: Console
Classifier: Intended Audience :: Developers
Classifier: License :: OSI Approved :: MIT License
Classifier: Programming Language :: Python
Classifier: Topic :: Documentation
Classifier: Topic :: File Formats :: JSON
Classifier: Topic :: Software Development :: Documentation
Requires-Python: >=3.8
Requires-Dist: iniconfig
Requires-Dist: packaging
Requires-Dist: pluggy
Requires-Dist: pytest
